{
    "snow":[
        {
            "Username":"admin",
            "Endpoint":"incident",
            "RecordCount":"1000",
            "ServerURL":"https://ven01034.service-now.com",
            "ProxyPassword":"",
            "ProxyURL":"",
            "ProxyUsername":"",
            "TimestampField":"sys_updated_on",
            "Password":"splunk123",
            "NextRecordTime":"2014-01-01+00:00:00",
            "Interval": "60",
            "App":"snow"
        },
        {
            "Username":"admin",
            "Endpoint":"problem",
            "RecordCount":"1000",
            "ServerURL":"https://ven01034.service-now.com",
            "ProxyPassword":"",
            "ProxyURL":"",
            "ProxyUsername":"",
            "TimestampField":"sys_updated_on",
            "Password":"splunk123",
            "NextRecordTime":"2014-01-01+00:00:00",
            "Interval": "60",
            "App":"snow"
        },
        {
            "Username":"admin",
            "Endpoint":"em_event",
            "RecordCount":"1000",
            "ServerURL":"https://ven01034.service-now.com",
            "ProxyPassword":"",
            "ProxyURL":"",
            "ProxyUsername":"",
            "TimestampField":"time_of_event",
            "Password":"splunk123",
            "NextRecordTime":"2014-01-01+00:00:00",
            "Interval": "60",
            "App":"snow"
        },
        {
            "Username":"admin",
            "Endpoint":"sys_user_group_list",
            "RecordCount":"1000",
            "ServerURL":"https://ven01034.service-now.com",
            "ProxyPassword":"",
            "ProxyURL":"",
            "ProxyUsername":"",
            "TimestampField":"sys_updated_on",
            "Password":"splunk123",
            "NextRecordTime":"2014-01-01+00:00:00",
            "Interval": "60",
            "App":"snow"
        },
        {
            "Username":"admin",
            "Endpoint":"sys_user_list",
            "RecordCount":"1000",
            "ServerURL":"https://ven01034.service-now.com",
            "ProxyPassword":"",
            "ProxyURL":"",
            "ProxyUsername":"",
            "TimestampField":"sys_updated_on",
            "Password":"splunk123",
            "NextRecordTime":"2014-01-01+00:00:00",
            "Interval": "60",
            "App":"snow"
        },
        {
            "Username":"admin",
            "Endpoint":"change_task",
            "RecordCount":"1000",
            "ServerURL":"https://ven01034.service-now.com",
            "ProxyPassword":"",
            "ProxyURL":"",
            "ProxyUsername":"",
            "TimestampField":"sys_updated_on",
            "Password":"splunk123",
            "NextRecordTime":"2014-01-01+00:00:00",
            "Interval": "60",
            "App":"snow"
        },
        {
            "Username":"admin",
            "Endpoint":"change_request",
            "RecordCount":"1000",
            "ServerURL":"https://ven01034.service-now.com",
            "ProxyPassword":"",
            "ProxyURL":"",
            "ProxyUsername":"",
            "TimestampField":"sys_updated_on",
            "Password":"splunk123",
            "NextRecordTime":"2014-01-01+00:00:00",
            "Interval": "60",
            "App":"snow"
        },
        {
            "Username":"admin",
            "Endpoint":"cmn_location_list",
            "RecordCount":"1000",
            "ServerURL":"https://ven01034.service-now.com",
            "ProxyPassword":"",
            "ProxyURL":"",
            "ProxyUsername":"",
            "TimestampField":"sys_updated_on",
            "Password":"splunk123",
            "NextRecordTime":"2014-01-01+00:00:00",
            "Interval": "60",
            "App":"snow"
        },
        {
            "Username":"admin",
            "Endpoint":"cmdb_ci_list",
            "RecordCount":"1000",
            "ServerURL":"https://ven01034.service-now.com",
            "ProxyPassword":"",
            "ProxyURL":"",
            "ProxyUsername":"",
            "TimestampField":"sys_updated_on",
            "Password":"splunk123",
            "NextRecordTime":"2014-01-01+00:00:00",
            "Interval": "60",
            "App":"snow"
        },
        {
            "Username":"admin",
            "Endpoint":"cmdb_ci_server",
            "RecordCount":"1000",
            "ServerURL":"https://ven01034.service-now.com",
            "ProxyPassword":"",
            "ProxyURL":"",
            "ProxyUsername":"",
            "TimestampField":"sys_updated_on",
            "Password":"splunk123",
            "NextRecordTime":"2014-01-01+00:00:00",
            "Interval": "60",
            "App":"snow"
        },
        {
            "Username":"admin",
            "Endpoint":"cmdb_ci_vm",
            "RecordCount":"1000",
            "ServerURL":"https://ven01034.service-now.com",
            "ProxyPassword":"",
            "ProxyURL":"",
            "ProxyUsername":"",
            "TimestampField":"sys_updated_on",
            "Password":"splunk123",
            "NextRecordTime":"2014-01-01+00:00:00",
            "Interval": "60",
            "App":"snow"
        },
        {
            "Username":"admin",
            "Endpoint":"cmdb_ci_infra_service",
            "RecordCount":"1000",
            "ServerURL":"https://ven01034.service-now.com",
            "ProxyPassword":"",
            "ProxyURL":"",
            "ProxyUsername":"",
            "TimestampField":"sys_updated_on",
            "Password":"splunk123",
            "NextRecordTime":"2014-01-01+00:00:00",
            "Interval": "60",
            "App":"snow"
        },
        {
            "Username":"admin",
            "Endpoint":"cmdb_ci_db_instance",
            "RecordCount":"1000",
            "ServerURL":"https://ven01034.service-now.com",
            "ProxyPassword":"",
            "ProxyURL":"",
            "ProxyUsername":"",
            "TimestampField":"sys_updated_on",
            "Password":"splunk123",
            "NextRecordTime":"2014-01-01+00:00:00",
            "Interval": "60",
            "App":"snow"
        },
        {
            "Username":"admin",
            "Endpoint":"cmdb_ci_app_server",
            "RecordCount":"1000",
            "ServerURL":"https://ven01034.service-now.com",
            "ProxyPassword":"",
            "ProxyURL":"",
            "ProxyUsername":"",
            "TimestampField":"sys_updated_on",
            "Password":"splunk123",
            "NextRecordTime":"2014-01-01+00:00:00",
            "Interval": "60",
            "App":"snow"
        },
        {
            "Username":"admin",
            "Endpoint":"cmdb_ci_service",
            "RecordCount":"1000",
            "ServerURL":"https://ven01034.service-now.com",
            "ProxyPassword":"",
            "ProxyURL":"",
            "ProxyUsername":"",
            "TimestampField":"sys_updated_on",
            "Password":"splunk123",
            "NextRecordTime":"2014-01-01+00:00:00",
            "Interval": "60",
            "App":"snow"
        },
        {
            "Username":"admin",
            "Endpoint":"cmdb_rel_ci",
            "RecordCount":"1000",
            "ServerURL":"https://ven01034.service-now.com",
            "ProxyPassword":"",
            "ProxyURL":"",
            "ProxyUsername":"",
            "TimestampField":"sys_updated_on",
            "Password":"splunk123",
            "NextRecordTime":"2014-01-01+00:00:00",
            "Interval": "60",
            "App":"snow"
        },
        {
            "Username":"admin",
            "Endpoint":"sys_choice_list",
            "RecordCount":"1000",
            "ServerURL":"https://ven01034.service-now.com",
            "ProxyPassword":"",
            "ProxyURL":"",
            "ProxyUsername":"",
            "TimestampField":"sys_updated_on",
            "Password":"splunk123",
            "NextRecordTime":"2014-01-01+00:00:00",
            "Interval": "60",
            "App":"snow"
        },
        {
            "Username":"admin",
            "Endpoint":"syslog",
            "RecordCount":"1000",
            "ServerURL":"https://ven01034.service-now.com",
            "ProxyPassword":"",
            "ProxyURL":"",
            "ProxyUsername":"",
            "TimestampField":"sys_created_on",
            "Password":"splunk123",
            "NextRecordTime":"2014-01-01+00:00:00",
            "Interval": "60",
            "App":"snow"
        },
        {
            "Username":"admin",
            "Endpoint":"syslog_transaction",
            "RecordCount":"1000",
            "ServerURL":"https://ven01034.service-now.com",
            "ProxyPassword":"",
            "ProxyURL":"",
            "ProxyUsername":"",
            "TimestampField":"sys_created_on",
            "Password":"splunk123",
            "NextRecordTime":"2014-01-01+00:00:00",
            "Interval": "60",
            "App":"snow"
        },
        {
            "Username":"admin",
            "Endpoint":"sys_audit",
            "RecordCount":"1000",
            "ServerURL":"https://ven01034.service-now.com",
            "ProxyPassword":"",
            "ProxyURL":"",
            "ProxyUsername":"",
            "TimestampField":"sys_created_on",
            "Password":"splunk123",
            "NextRecordTime":"2014-01-01+00:00:00",
            "Interval": "60",
            "App":"snow"
        },
        {
            "Username":"admin",
            "Endpoint":"incident",
            "RecordCount":"1000",
            "ServerURL":"https://dev166.service-now.com",
            "ProxyPassword":"",
            "ProxyURL":"",
            "ProxyUsername":"",
            "TimestampField":"sys_updated_on",
            "Password":"6DVbQtndiCUv",
            "NextRecordTime":"2014-01-01+00:00:00",
            "Interval": "60",
            "App":"snow"
        },
        {
            "Username":"admin",
            "Endpoint":"problem",
            "RecordCount":"1000",
            "ServerURL":"https://dev166.service-now.com",
            "ProxyPassword":"",
            "ProxyURL":"",
            "ProxyUsername":"",
            "TimestampField":"sys_updated_on",
            "Password":"6DVbQtndiCUv",
            "NextRecordTime":"2014-01-01+00:00:00",
            "Interval": "60",
            "App":"snow"
        },
        {
            "Username":"admin",
            "Endpoint":"em_event",
            "RecordCount":"1000",
            "ServerURL":"https://dev166.service-now.com",
            "ProxyPassword":"",
            "ProxyURL":"",
            "ProxyUsername":"",
            "TimestampField":"time_of_event",
            "Password":"6DVbQtndiCUv",
            "NextRecordTime":"2014-01-01+00:00:00",
            "Interval": "60",
            "App":"snow"
        },
        {
            "Username":"admin",
            "Endpoint":"sys_user_group_list",
            "RecordCount":"1000",
            "ServerURL":"https://dev166.service-now.com",
            "ProxyPassword":"",
            "ProxyURL":"",
            "ProxyUsername":"",
            "TimestampField":"sys_updated_on",
            "Password":"6DVbQtndiCUv",
            "NextRecordTime":"2014-01-01+00:00:00",
            "Interval": "60",
            "App":"snow"
        },
        {
            "Username":"admin",
            "Endpoint":"sys_user_list",
            "RecordCount":"1000",
            "ServerURL":"https://dev166.service-now.com",
            "ProxyPassword":"",
            "ProxyURL":"",
            "ProxyUsername":"",
            "TimestampField":"sys_updated_on",
            "Password":"6DVbQtndiCUv",
            "NextRecordTime":"2014-01-01+00:00:00",
            "Interval": "60",
            "App":"snow"
        },
        {
            "Username":"admin",
            "Endpoint":"change_task",
            "RecordCount":"1000",
            "ServerURL":"https://dev166.service-now.com",
            "ProxyPassword":"",
            "ProxyURL":"",
            "ProxyUsername":"",
            "TimestampField":"sys_updated_on",
            "Password":"6DVbQtndiCUv",
            "NextRecordTime":"2014-01-01+00:00:00",
            "Interval": "60",
            "App":"snow"
        },
        {
            "Username":"admin",
            "Endpoint":"change_request",
            "RecordCount":"1000",
            "ServerURL":"https://dev166.service-now.com",
            "ProxyPassword":"",
            "ProxyURL":"",
            "ProxyUsername":"",
            "TimestampField":"sys_updated_on",
            "Password":"6DVbQtndiCUv",
            "NextRecordTime":"2014-01-01+00:00:00",
            "Interval": "60",
            "App":"snow"
        },
        {
            "Username":"admin",
            "Endpoint":"cmn_location_list",
            "RecordCount":"1000",
            "ServerURL":"https://dev166.service-now.com",
            "ProxyPassword":"",
            "ProxyURL":"",
            "ProxyUsername":"",
            "TimestampField":"sys_updated_on",
            "Password":"6DVbQtndiCUv",
            "NextRecordTime":"2014-01-01+00:00:00",
            "Interval": "60",
            "App":"snow"
        },
        {
            "Username":"admin",
            "Endpoint":"cmdb_ci_list",
            "RecordCount":"1000",
            "ServerURL":"https://dev166.service-now.com",
            "ProxyPassword":"",
            "ProxyURL":"",
            "ProxyUsername":"",
            "TimestampField":"sys_updated_on",
            "Password":"6DVbQtndiCUv",
            "NextRecordTime":"2014-01-01+00:00:00",
            "Interval": "60",
            "App":"snow"
        },
        {
            "Username":"admin",
            "Endpoint":"cmdb_ci_server",
            "RecordCount":"1000",
            "ServerURL":"https://dev166.service-now.com",
            "ProxyPassword":"",
            "ProxyURL":"",
            "ProxyUsername":"",
            "TimestampField":"sys_updated_on",
            "Password":"6DVbQtndiCUv",
            "NextRecordTime":"2014-01-01+00:00:00",
            "Interval": "60",
            "App":"snow"
        },
        {
            "Username":"admin",
            "Endpoint":"cmdb_ci_vm",
            "RecordCount":"1000",
            "ServerURL":"https://dev166.service-now.com",
            "ProxyPassword":"",
            "ProxyURL":"",
            "ProxyUsername":"",
            "TimestampField":"sys_updated_on",
            "Password":"6DVbQtndiCUv",
            "NextRecordTime":"2014-01-01+00:00:00",
            "Interval": "60",
            "App":"snow"
        },
        {
            "Username":"admin",
            "Endpoint":"cmdb_ci_infra_service",
            "RecordCount":"1000",
            "ServerURL":"https://dev166.service-now.com",
            "ProxyPassword":"",
            "ProxyURL":"",
            "ProxyUsername":"",
            "TimestampField":"sys_updated_on",
            "Password":"6DVbQtndiCUv",
            "NextRecordTime":"2014-01-01+00:00:00",
            "Interval": "60",
            "App":"snow"
        },
        {
            "Username":"admin",
            "Endpoint":"cmdb_ci_db_instance",
            "RecordCount":"1000",
            "ServerURL":"https://dev166.service-now.com",
            "ProxyPassword":"",
            "ProxyURL":"",
            "ProxyUsername":"",
            "TimestampField":"sys_updated_on",
            "Password":"6DVbQtndiCUv",
            "NextRecordTime":"2014-01-01+00:00:00",
            "Interval": "60",
            "App":"snow"
        },
        {
            "Username":"admin",
            "Endpoint":"cmdb_ci_app_server",
            "RecordCount":"1000",
            "ServerURL":"https://dev166.service-now.com",
            "ProxyPassword":"",
            "ProxyURL":"",
            "ProxyUsername":"",
            "TimestampField":"sys_updated_on",
            "Password":"6DVbQtndiCUv",
            "NextRecordTime":"2014-01-01+00:00:00",
            "Interval": "60",
            "App":"snow"
        },
        {
            "Username":"admin",
            "Endpoint":"cmdb_ci_service",
            "RecordCount":"1000",
            "ServerURL":"https://dev166.service-now.com",
            "ProxyPassword":"",
            "ProxyURL":"",
            "ProxyUsername":"",
            "TimestampField":"sys_updated_on",
            "Password":"6DVbQtndiCUv",
            "NextRecordTime":"2014-01-01+00:00:00",
            "Interval": "60",
            "App":"snow"
        },
        {
            "Username":"admin",
            "Endpoint":"cmdb_rel_ci",
            "RecordCount":"1000",
            "ServerURL":"https://dev166.service-now.com",
            "ProxyPassword":"",
            "ProxyURL":"",
            "ProxyUsername":"",
            "TimestampField":"sys_updated_on",
            "Password":"6DVbQtndiCUv",
            "NextRecordTime":"2014-01-01+00:00:00",
            "Interval": "60",
            "App":"snow"
        },
        {
            "Username":"admin",
            "Endpoint":"sys_choice_list",
            "RecordCount":"1000",
            "ServerURL":"https://dev166.service-now.com",
            "ProxyPassword":"",
            "ProxyURL":"",
            "ProxyUsername":"",
            "TimestampField":"sys_updated_on",
            "Password":"6DVbQtndiCUv",
            "NextRecordTime":"2014-01-01+00:00:00",
            "Interval": "60",
            "App":"snow"
        },
        {
            "Username":"admin",
            "Endpoint":"syslog",
            "RecordCount":"1000",
            "ServerURL":"https://dev166.service-now.com",
            "ProxyPassword":"",
            "ProxyURL":"",
            "ProxyUsername":"",
            "TimestampField":"sys_created_on",
            "Password":"6DVbQtndiCUv",
            "NextRecordTime":"2014-01-01+00:00:00",
            "Interval": "60",
            "App":"snow"
        },
        {
            "Username":"admin",
            "Endpoint":"syslog_transaction",
            "RecordCount":"1000",
            "ServerURL":"https://dev166.service-now.com",
            "ProxyPassword":"",
            "ProxyURL":"",
            "ProxyUsername":"",
            "TimestampField":"sys_created_on",
            "Password":"6DVbQtndiCUv",
            "NextRecordTime":"2014-01-01+00:00:00",
            "Interval": "60",
            "App":"snow"
        },
        {
            "Username":"admin",
            "Endpoint":"sys_audit",
            "RecordCount":"1000",
            "ServerURL":"https://dev166.service-now.com",
            "ProxyPassword":"",
            "ProxyURL":"",
            "ProxyUsername":"",
            "TimestampField":"sys_created_on",
            "Password":"6DVbQtndiCUv",
            "NextRecordTime":"2014-01-01+00:00:00",
            "Interval": "60",
            "App":"snow"
        },
        {
            "Username":"admin",
            "Endpoint":"incident",
            "RecordCount":"1000",
            "ServerURL":"https://dev149.service-now.com",
            "ProxyPassword":"",
            "ProxyURL":"",
            "ProxyUsername":"",
            "TimestampField":"sys_updated_on",
            "Password":"b9CQn4paMYWp",
            "NextRecordTime":"2014-01-01+00:00:00",
            "Interval": "60",
            "App":"snow"
        },
        {
            "Username":"admin",
            "Endpoint":"problem",
            "RecordCount":"1000",
            "ServerURL":"https://dev149.service-now.com",
            "ProxyPassword":"",
            "ProxyURL":"",
            "ProxyUsername":"",
            "TimestampField":"sys_updated_on",
            "Password":"b9CQn4paMYWp",
            "NextRecordTime":"2014-01-01+00:00:00",
            "Interval": "60",
            "App":"snow"
        },
        {
            "Username":"admin",
            "Endpoint":"sys_user_group_list",
            "RecordCount":"1000",
            "ServerURL":"https://dev149.service-now.com",
            "ProxyPassword":"",
            "ProxyURL":"",
            "ProxyUsername":"",
            "TimestampField":"sys_updated_on",
            "Password":"b9CQn4paMYWp",
            "NextRecordTime":"2014-01-01+00:00:00",
            "Interval": "60",
            "App":"snow"
        },
        {
            "Username":"admin",
            "Endpoint":"sys_user_list",
            "RecordCount":"1000",
            "ServerURL":"https://dev149.service-now.com",
            "ProxyPassword":"",
            "ProxyURL":"",
            "ProxyUsername":"",
            "TimestampField":"sys_updated_on",
            "Password":"b9CQn4paMYWp",
            "NextRecordTime":"2014-01-01+00:00:00",
            "Interval": "60",
            "App":"snow"
        },
        {
            "Username":"admin",
            "Endpoint":"change_task",
            "RecordCount":"1000",
            "ServerURL":"https://dev149.service-now.com",
            "ProxyPassword":"",
            "ProxyURL":"",
            "ProxyUsername":"",
            "TimestampField":"sys_updated_on",
            "Password":"b9CQn4paMYWp",
            "NextRecordTime":"2014-01-01+00:00:00",
            "Interval": "60",
            "App":"snow"
        },
        {
            "Username":"admin",
            "Endpoint":"change_request",
            "RecordCount":"1000",
            "ServerURL":"https://dev149.service-now.com",
            "ProxyPassword":"",
            "ProxyURL":"",
            "ProxyUsername":"",
            "TimestampField":"sys_updated_on",
            "Password":"b9CQn4paMYWp",
            "NextRecordTime":"2014-01-01+00:00:00",
            "Interval": "60",
            "App":"snow"
        },
        {
            "Username":"admin",
            "Endpoint":"cmn_location_list",
            "RecordCount":"1000",
            "ServerURL":"https://dev149.service-now.com",
            "ProxyPassword":"",
            "ProxyURL":"",
            "ProxyUsername":"",
            "TimestampField":"sys_updated_on",
            "Password":"b9CQn4paMYWp",
            "NextRecordTime":"2014-01-01+00:00:00",
            "Interval": "60",
            "App":"snow"
        },
        {
            "Username":"admin",
            "Endpoint":"cmdb_ci_list",
            "RecordCount":"1000",
            "ServerURL":"https://dev149.service-now.com",
            "ProxyPassword":"",
            "ProxyURL":"",
            "ProxyUsername":"",
            "TimestampField":"sys_updated_on",
            "Password":"b9CQn4paMYWp",
            "NextRecordTime":"2014-01-01+00:00:00",
            "Interval": "60",
            "App":"snow"
        },
        {
            "Username":"admin",
            "Endpoint":"cmdb_ci_server",
            "RecordCount":"1000",
            "ServerURL":"https://dev149.service-now.com",
            "ProxyPassword":"",
            "ProxyURL":"",
            "ProxyUsername":"",
            "TimestampField":"sys_updated_on",
            "Password":"b9CQn4paMYWp",
            "NextRecordTime":"2014-01-01+00:00:00",
            "Interval": "60",
            "App":"snow"
        },
        {
            "Username":"admin",
            "Endpoint":"cmdb_ci_vm",
            "RecordCount":"1000",
            "ServerURL":"https://dev149.service-now.com",
            "ProxyPassword":"",
            "ProxyURL":"",
            "ProxyUsername":"",
            "TimestampField":"sys_updated_on",
            "Password":"b9CQn4paMYWp",
            "NextRecordTime":"2014-01-01+00:00:00",
            "Interval": "60",
            "App":"snow"
        },
        {
            "Username":"admin",
            "Endpoint":"cmdb_ci_infra_service",
            "RecordCount":"1000",
            "ServerURL":"https://dev149.service-now.com",
            "ProxyPassword":"",
            "ProxyURL":"",
            "ProxyUsername":"",
            "TimestampField":"sys_updated_on",
            "Password":"b9CQn4paMYWp",
            "NextRecordTime":"2014-01-01+00:00:00",
            "Interval": "60",
            "App":"snow"
        },
        {
            "Username":"admin",
            "Endpoint":"cmdb_ci_db_instance",
            "RecordCount":"1000",
            "ServerURL":"https://dev149.service-now.com",
            "ProxyPassword":"",
            "ProxyURL":"",
            "ProxyUsername":"",
            "TimestampField":"sys_updated_on",
            "Password":"b9CQn4paMYWp",
            "NextRecordTime":"2014-01-01+00:00:00",
            "Interval": "60",
            "App":"snow"
        },
        {
            "Username":"admin",
            "Endpoint":"cmdb_ci_app_server",
            "RecordCount":"1000",
            "ServerURL":"https://dev149.service-now.com",
            "ProxyPassword":"",
            "ProxyURL":"",
            "ProxyUsername":"",
            "TimestampField":"sys_updated_on",
            "Password":"b9CQn4paMYWp",
            "NextRecordTime":"2014-01-01+00:00:00",
            "Interval": "60",
            "App":"snow"
        },
        {
            "Username":"admin",
            "Endpoint":"cmdb_ci_service",
            "RecordCount":"1000",
            "ServerURL":"https://dev149.service-now.com",
            "ProxyPassword":"",
            "ProxyURL":"",
            "ProxyUsername":"",
            "TimestampField":"sys_updated_on",
            "Password":"b9CQn4paMYWp",
            "NextRecordTime":"2014-01-01+00:00:00",
            "Interval": "60",
            "App":"snow"
        },
        {
            "Username":"admin",
            "Endpoint":"cmdb_rel_ci",
            "RecordCount":"1000",
            "ServerURL":"https://dev149.service-now.com",
            "ProxyPassword":"",
            "ProxyURL":"",
            "ProxyUsername":"",
            "TimestampField":"sys_updated_on",
            "Password":"b9CQn4paMYWp",
            "NextRecordTime":"2014-01-01+00:00:00",
            "Interval": "60",
            "App":"snow"
        },
        {
            "Username":"admin",
            "Endpoint":"sys_choice_list",
            "RecordCount":"1000",
            "ServerURL":"https://dev149.service-now.com",
            "ProxyPassword":"",
            "ProxyURL":"",
            "ProxyUsername":"",
            "TimestampField":"sys_updated_on",
            "Password":"b9CQn4paMYWp",
            "NextRecordTime":"2014-01-01+00:00:00",
            "Interval": "60",
            "App":"snow"
        },
        {
            "Username":"admin",
            "Endpoint":"syslog",
            "RecordCount":"1000",
            "ServerURL":"https://dev149.service-now.com",
            "ProxyPassword":"",
            "ProxyURL":"",
            "ProxyUsername":"",
            "TimestampField":"sys_created_on",
            "Password":"b9CQn4paMYWp",
            "NextRecordTime":"2014-01-01+00:00:00",
            "Interval": "60",
            "App":"snow"
        },
        {
            "Username":"admin",
            "Endpoint":"syslog_transaction",
            "RecordCount":"1000",
            "ServerURL":"https://dev149.service-now.com",
            "ProxyPassword":"",
            "ProxyURL":"",
            "ProxyUsername":"",
            "TimestampField":"sys_created_on",
            "Password":"b9CQn4paMYWp",
            "NextRecordTime":"2014-01-01+00:00:00",
            "Interval": "60",
            "App":"snow"
        },
        {
            "Username":"admin",
            "Endpoint":"sys_audit",
            "RecordCount":"1000",
            "ServerURL":"https://dev149.service-now.com",
            "ProxyPassword":"",
            "ProxyURL":"",
            "ProxyUsername":"",
            "TimestampField":"sys_created_on",
            "Password":"b9CQn4paMYWp",
            "NextRecordTime":"2014-01-01+00:00:00",
            "Interval": "60",
            "App":"snow"
        },
        {
            "Username":"admin",
            "Endpoint":"incident",
            "RecordCount":"1000",
            "ServerURL":"https://dev167.service-now.com",
            "ProxyPassword":"",
            "ProxyURL":"",
            "ProxyUsername":"",
            "TimestampField":"sys_updated_on",
            "Password":"7RowgWED34FQ",
            "NextRecordTime":"2014-01-01+00:00:00",
            "Interval": "60",
            "App":"snow"
        },
        {
            "Username":"admin",
            "Endpoint":"problem",
            "RecordCount":"1000",
            "ServerURL":"https://dev167.service-now.com",
            "ProxyPassword":"",
            "ProxyURL":"",
            "ProxyUsername":"",
            "TimestampField":"sys_updated_on",
            "Password":"7RowgWED34FQ",
            "NextRecordTime":"2014-01-01+00:00:00",
            "Interval": "60",
            "App":"snow"
        },
        {
            "Username":"admin",
            "Endpoint":"sys_user_group_list",
            "RecordCount":"1000",
            "ServerURL":"https://dev167.service-now.com",
            "ProxyPassword":"",
            "ProxyURL":"",
            "ProxyUsername":"",
            "TimestampField":"sys_updated_on",
            "Password":"7RowgWED34FQ",
            "NextRecordTime":"2014-01-01+00:00:00",
            "Interval": "60",
            "App":"snow"
        },
        {
            "Username":"admin",
            "Endpoint":"sys_user_list",
            "RecordCount":"1000",
            "ServerURL":"https://dev167.service-now.com",
            "ProxyPassword":"",
            "ProxyURL":"",
            "ProxyUsername":"",
            "TimestampField":"sys_updated_on",
            "Password":"7RowgWED34FQ",
            "NextRecordTime":"2014-01-01+00:00:00",
            "Interval": "60",
            "App":"snow"
        },
        {
            "Username":"admin",
            "Endpoint":"change_task",
            "RecordCount":"1000",
            "ServerURL":"https://dev167.service-now.com",
            "ProxyPassword":"",
            "ProxyURL":"",
            "ProxyUsername":"",
            "TimestampField":"sys_updated_on",
            "Password":"7RowgWED34FQ",
            "NextRecordTime":"2014-01-01+00:00:00",
            "Interval": "60",
            "App":"snow"
        },
        {
            "Username":"admin",
            "Endpoint":"change_request",
            "RecordCount":"1000",
            "ServerURL":"https://dev167.service-now.com",
            "ProxyPassword":"",
            "ProxyURL":"",
            "ProxyUsername":"",
            "TimestampField":"sys_updated_on",
            "Password":"7RowgWED34FQ",
            "NextRecordTime":"2014-01-01+00:00:00",
            "Interval": "60",
            "App":"snow"
        },
        {
            "Username":"admin",
            "Endpoint":"cmn_location_list",
            "RecordCount":"1000",
            "ServerURL":"https://dev167.service-now.com",
            "ProxyPassword":"",
            "ProxyURL":"",
            "ProxyUsername":"",
            "TimestampField":"sys_updated_on",
            "Password":"7RowgWED34FQ",
            "NextRecordTime":"2014-01-01+00:00:00",
            "Interval": "60",
            "App":"snow"
        },
        {
            "Username":"admin",
            "Endpoint":"cmdb_ci_list",
            "RecordCount":"1000",
            "ServerURL":"https://dev167.service-now.com",
            "ProxyPassword":"",
            "ProxyURL":"",
            "ProxyUsername":"",
            "TimestampField":"sys_updated_on",
            "Password":"7RowgWED34FQ",
            "NextRecordTime":"2014-01-01+00:00:00",
            "Interval": "60",
            "App":"snow"
        },
        {
            "Username":"admin",
            "Endpoint":"cmdb_ci_server",
            "RecordCount":"1000",
            "ServerURL":"https://dev167.service-now.com",
            "ProxyPassword":"",
            "ProxyURL":"",
            "ProxyUsername":"",
            "TimestampField":"sys_updated_on",
            "Password":"7RowgWED34FQ",
            "NextRecordTime":"2014-01-01+00:00:00",
            "Interval": "60",
            "App":"snow"
        },
        {
            "Username":"admin",
            "Endpoint":"cmdb_ci_vm",
            "RecordCount":"1000",
            "ServerURL":"https://dev167.service-now.com",
            "ProxyPassword":"",
            "ProxyURL":"",
            "ProxyUsername":"",
            "TimestampField":"sys_updated_on",
            "Password":"7RowgWED34FQ",
            "NextRecordTime":"2014-01-01+00:00:00",
            "Interval": "60",
            "App":"snow"
        },
        {
            "Username":"admin",
            "Endpoint":"cmdb_ci_infra_service",
            "RecordCount":"1000",
            "ServerURL":"https://dev167.service-now.com",
            "ProxyPassword":"",
            "ProxyURL":"",
            "ProxyUsername":"",
            "TimestampField":"sys_updated_on",
            "Password":"7RowgWED34FQ",
            "NextRecordTime":"2014-01-01+00:00:00",
            "Interval": "60",
            "App":"snow"
        },
        {
            "Username":"admin",
            "Endpoint":"cmdb_ci_db_instance",
            "RecordCount":"1000",
            "ServerURL":"https://dev167.service-now.com",
            "ProxyPassword":"",
            "ProxyURL":"",
            "ProxyUsername":"",
            "TimestampField":"sys_updated_on",
            "Password":"7RowgWED34FQ",
            "NextRecordTime":"2014-01-01+00:00:00",
            "Interval": "60",
            "App":"snow"
        },
        {
            "Username":"admin",
            "Endpoint":"cmdb_ci_app_server",
            "RecordCount":"1000",
            "ServerURL":"https://dev167.service-now.com",
            "ProxyPassword":"",
            "ProxyURL":"",
            "ProxyUsername":"",
            "TimestampField":"sys_updated_on",
            "Password":"7RowgWED34FQ",
            "NextRecordTime":"2014-01-01+00:00:00",
            "Interval": "60",
            "App":"snow"
        },
        {
            "Username":"admin",
            "Endpoint":"cmdb_ci_service",
            "RecordCount":"1000",
            "ServerURL":"https://dev167.service-now.com",
            "ProxyPassword":"",
            "ProxyURL":"",
            "ProxyUsername":"",
            "TimestampField":"sys_updated_on",
            "Password":"7RowgWED34FQ",
            "NextRecordTime":"2014-01-01+00:00:00",
            "Interval": "60",
            "App":"snow"
        },
        {
            "Username":"admin",
            "Endpoint":"cmdb_rel_ci",
            "RecordCount":"1000",
            "ServerURL":"https://dev167.service-now.com",
            "ProxyPassword":"",
            "ProxyURL":"",
            "ProxyUsername":"",
            "TimestampField":"sys_updated_on",
            "Password":"7RowgWED34FQ",
            "NextRecordTime":"2014-01-01+00:00:00",
            "Interval": "60",
            "App":"snow"
        },
        {
            "Username":"admin",
            "Endpoint":"sys_choice_list",
            "RecordCount":"1000",
            "ServerURL":"https://dev167.service-now.com",
            "ProxyPassword":"",
            "ProxyURL":"",
            "ProxyUsername":"",
            "TimestampField":"sys_updated_on",
            "Password":"7RowgWED34FQ",
            "NextRecordTime":"2014-01-01+00:00:00",
            "Interval": "60",
            "App":"snow"
        },
        {
            "Username":"admin",
            "Endpoint":"syslog",
            "RecordCount":"1000",
            "ServerURL":"https://dev167.service-now.com",
            "ProxyPassword":"",
            "ProxyURL":"",
            "ProxyUsername":"",
            "TimestampField":"sys_created_on",
            "Password":"7RowgWED34FQ",
            "NextRecordTime":"2014-01-01+00:00:00",
            "Interval": "60",
            "App":"snow"
        },
        {
            "Username":"admin",
            "Endpoint":"syslog_transaction",
            "RecordCount":"1000",
            "ServerURL":"https://dev167.service-now.com",
            "ProxyPassword":"",
            "ProxyURL":"",
            "ProxyUsername":"",
            "TimestampField":"sys_created_on",
            "Password":"7RowgWED34FQ",
            "NextRecordTime":"2014-01-01+00:00:00",
            "Interval": "60",
            "App":"snow"
        },
        {
            "Username":"admin",
            "Endpoint":"sys_audit",
            "RecordCount":"1000",
            "ServerURL":"https://dev167.service-now.com",
            "ProxyPassword":"",
            "ProxyURL":"",
            "ProxyUsername":"",
            "TimestampField":"sys_created_on",
            "Password":"7RowgWED34FQ",
            "NextRecordTime":"2014-01-01+00:00:00",
            "Interval": "60",
            "App":"snow"
        }
    ]
}
